projects/UART_TX/FSM.v
module FSM (
    input wire       clk,
    input wire       rst,
    input wire       data_valid,
    input wire [3:0] bit_no,
    input wire       parity_en,

    output reg [1:0] MuX_cntrol,
    output reg       serial_en,
    output reg       busy_sig

);
    
localparam IDLE   =  3'b0,
           start  =  3'b001,
           data   =  3'b010,
           parity =  3'b011,
           stop   =  3'b100;

reg [2:0] state;
reg [2:0] next_state;

always @(posedge clk or negedge rst) 
    begin
        if (!rst) 
            state<=IDLE;
        else
            state<=next_state;
    end

always @(*)
    begin

        case (state)
            IDLE:
                begin
                    busy_sig=1'b0;
                    MuX_cntrol=2'b11; //output high
                    if (data_valid) 
                        begin
                            busy_sig=1'b1;
                            serial_en=1'b1;
                            next_state=start;
                            
    
                        end
                    else
                        next_state=IDLE;
                end

            start:
                begin
                    busy_sig=1'b1;
                    serial_en=1'b0;
                    MuX_cntrol=2'b00;
                    next_state=data;      
                end

            data:
                begin
                    busy_sig=1'b1;
                    serial_en=1'b0;
                    MuX_cntrol=2'b01; 
                       
                        if (bit_no<8) 
                            next_state=data;
                        else
                            begin
                                if (parity_en) 
                                    begin
                                        next_state=parity;
                                    end
                                else
                                    next_state=stop;
                            end
                            
                end 
            
            parity:
                begin
                    busy_sig=1'b1;
                    serial_en=1'b0;
                    MuX_cntrol=2'b10;
                    next_state=stop;
                end
            
            stop:
                begin
                    busy_sig=1'b1;
                    serial_en=1'b0;
                    MuX_cntrol=2'b11;
                    next_state=IDLE;

                end
            default: next_state=IDLE; 
        endcase


    end     
endmodule

projects/UART_TX/serializer.v
module serializer (
    input wire       clk,
    input wire       rst,
    input wire       load,
    input wire [7:0] s_input,

    output reg [3:0] bit_no,
    output reg       s_output

);
reg [7:0] temp;
always @(posedge clk or negedge rst)
 begin
     if (!rst) 
        begin
            temp<=8'b0;
            s_output<=1'b0;
            bit_no<=4'b0;
        end
     else

        begin
           if (load) 
                begin
                   temp<=s_input;
                   bit_no<=4'b0;
                end

            else
                begin
                    if (bit_no<=3'b111) 
                        begin
                          s_output<=temp[bit_no];
                          bit_no<=bit_no+1'b1; 
                        end
                    else
                        begin
                             s_output<=1'b0;
                        end
                end
        end
 end
endmodule

projects/UART_TX/parity.v
module parity (
    input wire [7:0] P_data,
    input wire       parity_type,
    output reg       parity_bit
);

always @(*)
    begin
        if (parity_type==0)  //even 
            
            parity_bit=^P_data;

        else
            parity_bit=~(^P_data); 
 
    end
endmodule

mux.v
module mux (
    input wire [1:0] sel,
    input wire       i1,
    input wire       i2,
    input wire       i3,
    input wire       i4,

    output reg       mux_out
);

always @(*) 
    begin
        case (sel)
            2'b00:mux_out=i1; 
            2'b01:mux_out=i2; 
            2'b10:mux_out=i3; 
            2'b11:mux_out=i4; 
        endcase    
    end  
endmodule

UART_TOP.v
module UART_TOP (

    input wire CLK,
    input wire RST,
    input wire [7:0] P_DATA,
    input wire       DATA_VALID,
    input wire       PAR_EN,
    input wire       PAR_TYP,

    output wire       S_DATA,
    output wire       BUSY


);

wire serial_en;
//wire serial_out;
wire [3:0] bit_no;


wire mux_i2;
wire mux_i3;

wire [1:0] mux_sel;

//wire parity_out;

mux MUX1(

    .sel(mux_sel),
    .i1(1'b0),
    .i2(mux_i2),
    .i3(mux_i3),
    .i4(1'b1),
    .mux_out(S_DATA)    

);

parity p1(

    .P_data(P_DATA),
    .parity_type(PAR_TYP),
    .parity_bit(mux_i3)

);

serializer s1(

    .clk(CLK),
    .rst(RST),
    .load(serial_en),
    .s_input(P_DATA),
    .bit_no(bit_no),
    .s_output(mux_i2)

);

FSM F1(

    .clk(CLK),
    .rst(RST),
    .data_valid(DATA_VALID),
    .bit_no(bit_no),
    .parity_en(PAR_EN),
    .MuX_cntrol(mux_sel),
    .serial_en(serial_en),
    .busy_sig(BUSY)
);
endmodule

UART_TOP_tb.v
`timescale 1ns/100ps
module UART_TOP_tb ();

reg CLK_tb;
reg RST_tb;
reg [7:0] P_DATA_tb;
reg       DATA_VALID_tb;
reg       PAR_EN_tb;
reg       PAR_TYP_tb;
wire       S_DATA_tb;
wire       BUSY_tb;


parameter clk_period=5;
  reg [10:0] value,data;


//initial block 

initial

    begin
        $dumpfile("UART_TOP.vcd");
        $dumpvars;
        
        CLK_tb=1'b0;

        
        RST_tb=1'b1;
        #clk_period
        RST_tb=1'b0;
        #clk_period
        RST_tb=1'b1;
        //initialization
      	DATA_VALID_tb=1'b0;
      	PAR_EN_tb=1'b0;
        PAR_TYP_tb=1'b0;
      	P_DATA_tb=8'b0;
      
    //testing
      //case 1
        $display("Test case 1 :Parity enabled & Even");
        P_DATA_tb=8'b0101011;
        data={1'b0,P_DATA_tb[0],P_DATA_tb[1],P_DATA_tb[2],P_DATA_tb[3],P_DATA_tb[4],P_DATA_tb[5],P_DATA_tb[6],
              P_DATA_tb[7],2'b01};
      	#clk_period
        $display("Data=%b",P_DATA_tb);
        DATA_VALID_tb=1'b1;
      	#clk_period
      	DATA_VALID_tb=1'b0;
        value={value,S_DATA_tb};
        PAR_EN_tb=1'b1;
        PAR_TYP_tb=1'b0;
        #clk_period
        value={value,S_DATA_tb};
        #clk_period
        value={value,S_DATA_tb};
        #clk_period
        value={value,S_DATA_tb};
        #clk_period
        value={value,S_DATA_tb};
        #clk_period
        value={value,S_DATA_tb};
        #clk_period
        value={value,S_DATA_tb};
        #clk_period
        value={value,S_DATA_tb};
        #clk_period
        value={value,S_DATA_tb};
        #clk_period
        value={value,S_DATA_tb};
        #clk_period
        value={value,S_DATA_tb};
        $display("Expected Frame=%b",data);
        #clk_period

        if (BUSY_tb==0)
            begin
                $display("Output Frame	=%b",value);
                if(value==data)
                $display("Case 1 successful");
                else  
                $display("Case 1 unsuccessful");
            end
      
      //Case2
        $display("\nTest case 2 :Parity enabled & Odd");
        P_DATA_tb=8'b0101011;
        data={1'b0,P_DATA_tb[0],P_DATA_tb[1],P_DATA_tb[2],P_DATA_tb[3],P_DATA_tb[4],P_DATA_tb[5],P_DATA_tb[6],
              P_DATA_tb[7],2'b11};
      	#clk_period
        $display("Data=%b",P_DATA_tb);
        DATA_VALID_tb=1'b1;
      	#clk_period
      	DATA_VALID_tb=1'b0;
        value={value,S_DATA_tb};
        PAR_EN_tb=1'b1;
        PAR_TYP_tb=1'b1;
        #clk_period
      	value={value,S_DATA_tb};
        #clk_period
        value={value,S_DATA_tb};
        #clk_period
        value={value,S_DATA_tb};
        #clk_period
        value={value,S_DATA_tb};
        #clk_period
        value={value,S_DATA_tb};
        #clk_period
        value={value,S_DATA_tb};
        #clk_period
        value={value,S_DATA_tb};
        #clk_period
        value={value,S_DATA_tb};
        #clk_period
        value={value,S_DATA_tb};
        #clk_period
        value={value,S_DATA_tb};
        $display("Expected Frame=%b",data);
        #clk_period

        if (BUSY_tb==0)
            begin
                $display("Output Frame	=%b",value);
                if(value==data)
                    $display("Case 2 successful");
                else  
                $display("Case 2 unsuccessful");
            end
        
      //case 3
     
        $display("\nTest case 3 :Parity disabled");
        P_DATA_tb=8'b0101011;
        data={1'b0,P_DATA_tb[0],P_DATA_tb[1],P_DATA_tb[2],P_DATA_tb[3],P_DATA_tb[4],P_DATA_tb[5],P_DATA_tb[6],
              P_DATA_tb[7],1'b1};
      	#clk_period
        $display("Data=%b",P_DATA_tb);
        DATA_VALID_tb=1'b1;
      	#clk_period
      	DATA_VALID_tb=1'b0;
        value={value,S_DATA_tb};
        PAR_EN_tb=1'b0;
        PAR_TYP_tb=1'b1;
        #clk_period
      	value={value,S_DATA_tb};
        #clk_period
        value={value,S_DATA_tb};
        #clk_period
        value={value,S_DATA_tb};
        #clk_period
        value={value,S_DATA_tb};
        #clk_period
        value={value,S_DATA_tb};
        #clk_period
        value={value,S_DATA_tb};
        #clk_period
        value={value,S_DATA_tb};
        #clk_period
        value={value,S_DATA_tb};
        #clk_period
        value={value,S_DATA_tb};
        $display("Expected Frame=%b",data[9:0]);
        #clk_period
      	

        if (BUSY_tb==0)
            begin
                $display("Output Frame	=%b",value[9:0]);
                if(value[9:0]==data[9:0])
                    $display("Case 3 successful");
                    else  
                    $display("Case 3 unsuccessful");
            end
        
    //Case4
        $display("\nTest case 4 :Data valid change during TX");
        P_DATA_tb=8'b0101011;
        data={1'b0,P_DATA_tb[0],P_DATA_tb[1],P_DATA_tb[2],P_DATA_tb[3],P_DATA_tb[4],P_DATA_tb[5],P_DATA_tb[6],
              P_DATA_tb[7],1'b1};
      	#clk_period
        $display("Data=%b",P_DATA_tb);
        DATA_VALID_tb=1'b1;
      	#clk_period
      	DATA_VALID_tb=1'b0;
        value={value,S_DATA_tb};
        PAR_EN_tb=1'b0;
        PAR_TYP_tb=1'b1;
        #clk_period
      	value={value,S_DATA_tb};
        #clk_period
        value={value,S_DATA_tb};
      	DATA_VALID_tb=1'b1;
      	P_DATA_tb=8'b0101001;
        #clk_period
      	DATA_VALID_tb=1'b0;
        value={value,S_DATA_tb};
        #clk_period
        value={value,S_DATA_tb};
        #clk_period
        value={value,S_DATA_tb};
        #clk_period
        value={value,S_DATA_tb};
        #clk_period
        value={value,S_DATA_tb};
        #clk_period
        value={value,S_DATA_tb};
        #clk_period
        value={value,S_DATA_tb};
        $display("Expected Frame=%b",data[9:0]);
        #clk_period
      	

        if (BUSY_tb==0)
            begin
                $display("Output Frame	=%b",value[9:0]);
                if(value[9:0]==data[9:0])
                    $display("Case 4 successful");
                    else  
                    $display("Case 4 unsuccessful");
            end
      
      $finish;
        
        

     
    end

//instantiate
UART_TOP DUT(

.CLK(CLK_tb),
.RST(RST_tb),
.P_DATA(P_DATA_tb),
.DATA_VALID(DATA_VALID_tb),
.PAR_EN(PAR_EN_tb),
.PAR_TYP(PAR_TYP_tb),
.S_DATA(S_DATA_tb),
.BUSY(BUSY_tb)
);


//clock generator //5ns ==200Mhz
always #(clk_period*0.5) CLK_tb=~CLK_tb;


endmodule

UART_TOP.vcd
$date
	Wed Jul 13 23:59:46 2022
$end
$version
	ModelSim Version 10.5b
$end
$timescale
	100ps
$end

$scope module UART_TOP_tb $end
$var parameter 32 ! clk_period $end
$var reg 1 " CLK_tb $end
$var reg 1 # RST_tb $end
$var reg 8 $ P_DATA_tb [7:0] $end
$var reg 1 % DATA_VALID_tb $end
$var reg 1 & PAR_EN_tb $end
$var reg 1 ' PAR_TYP_tb $end
$var wire 1 ( S_DATA_tb $end
$var wire 1 ) BUSY_tb $end
$var reg 11 * value [10:0] $end
$var reg 11 + data [10:0] $end

$scope module DUT $end
$var wire 1 , CLK $end
$var wire 1 - RST $end
$var wire 1 . P_DATA [7] $end
$var wire 1 / P_DATA [6] $end
$var wire 1 0 P_DATA [5] $end
$var wire 1 1 P_DATA [4] $end
$var wire 1 2 P_DATA [3] $end
$var wire 1 3 P_DATA [2] $end
$var wire 1 4 P_DATA [1] $end
$var wire 1 5 P_DATA [0] $end
$var wire 1 6 DATA_VALID $end
$var wire 1 7 PAR_EN $end
$var wire 1 8 PAR_TYP $end
$var wire 1 ( S_DATA $end
$var wire 1 ) BUSY $end
$var wire 1 9 serial_en $end
$var wire 1 : bit_no [3] $end
$var wire 1 ; bit_no [2] $end
$var wire 1 < bit_no [1] $end
$var wire 1 = bit_no [0] $end
$var wire 1 > mux_i2 $end
$var wire 1 ? mux_i3 $end
$var wire 1 @ mux_sel [1] $end
$var wire 1 A mux_sel [0] $end

$scope module MUX1 $end
$var wire 1 @ sel [1] $end
$var wire 1 A sel [0] $end
$var wire 1 B i1 $end
$var wire 1 > i2 $end
$var wire 1 ? i3 $end
$var wire 1 C i4 $end
$var reg 1 D mux_out $end
$upscope $end

$scope module p1 $end
$var wire 1 . P_data [7] $end
$var wire 1 / P_data [6] $end
$var wire 1 0 P_data [5] $end
$var wire 1 1 P_data [4] $end
$var wire 1 2 P_data [3] $end
$var wire 1 3 P_data [2] $end
$var wire 1 4 P_data [1] $end
$var wire 1 5 P_data [0] $end
$var wire 1 8 parity_type $end
$var reg 1 E parity_bit $end
$upscope $end

$scope module s1 $end
$var wire 1 , clk $end
$var wire 1 - rst $end
$var wire 1 9 load $end
$var wire 1 . s_input [7] $end
$var wire 1 / s_input [6] $end
$var wire 1 0 s_input [5] $end
$var wire 1 1 s_input [4] $end
$var wire 1 2 s_input [3] $end
$var wire 1 3 s_input [2] $end
$var wire 1 4 s_input [1] $end
$var wire 1 5 s_input [0] $end
$var reg 4 F bit_no [3:0] $end
$var reg 1 G s_output $end
$var reg 8 H temp [7:0] $end
$upscope $end

$scope module F1 $end
$var parameter 3 I IDLE $end
$var parameter 3 J start $end
$var parameter 3 K data $end
$var parameter 3 L parity $end
$var parameter 3 M stop $end
$var wire 1 , clk $end
$var wire 1 - rst $end
$var wire 1 6 data_valid $end
$var wire 1 : bit_no [3] $end
$var wire 1 ; bit_no [2] $end
$var wire 1 < bit_no [1] $end
$var wire 1 = bit_no [0] $end
$var wire 1 7 parity_en $end
$var reg 2 N MuX_cntrol [1:0] $end
$var reg 1 O serial_en $end
$var reg 1 P busy_sig $end
$var reg 3 Q state [2:0] $end
$var reg 3 R next_state [2:0] $end
$upscope $end
$upscope $end
$upscope $end
$enddefinitions $end
#0
$dumpvars
0"
1#
bx $
x%
x&
x'
bx *
bx +
xD
xE
bx F
xG
bx H
bx N
xO
xP
bx Q
bx R
b101 !
b0 I
b1 J
b10 K
b11 L
b100 M
x(
x)
x9
x=
x<
x;
x:
x>
x?
xA
x@
x8
x7
x6
x5
x4
x3
x2
x1
x0
x/
x.
1-
0,
1C
0B
$end
#25
1"
1,
0G
0>
#50
0#
0"
0-
0,
b0 H
b0 F
b0 Q
0=
0<
0;
0:
0P
b11 N
b0 R
0)
1A
1@
1D
1(
#75
1"
1,
#100
1#
0%
0&
0'
b0 $
b101011 $
b1101010001 +
0"
1-
06
07
08
15
14
03
12
01
10
0/
0.
0,
0E
0?
#125
1"
1,
b1 F
1=
#150
1%
0"
16
0,
1P
1O
b1 R
1)
19
#175
1"
1,
b101011 H
b0 F
b1 Q
0=
0O
b0 N
b10 R
09
0A
0@
0D
0(
#200
0%
bx0 *
1&
0"
06
17
0,
#225
1"
1,
1G
b1 F
b10 Q
1>
1=
b1 N
1A
1D
1(
#250
bx01 *
0"
0,
#275
1"
1,
b10 F
0=
1<
#300
bx011 *
0"
0,
#325
1"
1,
0G
b11 F
0>
1=
0D
0(
#350
bx0110 *
0"
0,
#375
1"
1,
1G
b100 F
1>
0=
0<
1;
1D
1(
#400
bx01101 *
0"
0,
#425
1"
1,
0G
b101 F
0>
1=
0D
0(
#450
bx011010 *
0"
0,
#475
1"
1,
1G
b110 F
1>
0=
1<
1D
1(
#500
bx0110101 *
0"
0,
#525
1"
1,
0G
b111 F
0>
1=
0D
0(
#550
bx01101010 *
0"
0,
#575
1"
1,
b1000 F
0=
0<
0;
1:
b11 R
#600
bx011010100 *
0"
0,
#625
1"
1,
b11 Q
b10 N
b100 R
0A
1@
#650
bx0110101000 *
0"
0,
#675
1"
1,
b100 Q
b11 N
b0 R
1A
1D
1(
#700
b1101010001 *
0"
0,
#725
1"
1,
b0 Q
0P
0)
#750
b1101010011 +
0"
0,
#775
1"
1,
#800
1%
0"
16
0,
1P
1O
b1 R
1)
19
#825
1"
1,
b0 F
b1 Q
0:
0O
b0 N
b10 R
09
0A
0@
0D
0(
#850
0%
b11010100010 *
1'
0"
06
18
0,
1E
1?
#875
1"
1,
1G
b1 F
b10 Q
1>
1=
b1 N
1A
1D
1(
#900
b10101000101 *
0"
0,
#925
1"
1,
b10 F
0=
1<
#950
b1010001011 *
0"
0,
#975
1"
1,
0G
b11 F
0>
1=
0D
0(
#1000
b10100010110 *
0"
0,
#1025
1"
1,
1G
b100 F
1>
0=
0<
1;
1D
1(
#1050
b1000101101 *
0"
0,
#1075
1"
1,
0G
b101 F
0>
1=
0D
0(
#1100
b10001011010 *
0"
0,
#1125
1"
1,
1G
b110 F
1>
0=
1<
1D
1(
#1150
b10110101 *
0"
0,
#1175
1"
1,
0G
b111 F
0>
1=
0D
0(
#1200
b101101010 *
0"
0,
#1225
1"
1,
b1000 F
0=
0<
0;
1:
b11 R
#1250
b1011010100 *
0"
0,
#1275
1"
1,
b11 Q
b10 N
b100 R
0A
1@
1D
1(
#1300
b10110101001 *
0"
0,
#1325
1"
1,
b100 Q
b11 N
b0 R
1A
#1350
b1101010011 *
0"
0,
#1375
1"
1,
b0 Q
0P
0)
#1400
b110101001 +
0"
0,
#1425
1"
1,
#1450
1%
0"
16
0,
1P
1O
b1 R
1)
19
#1475
1"
1,
b0 F
b1 Q
0:
0O
b0 N
b10 R
09
0A
0@
0D
0(
#1500
0%
b11010100110 *
0&
0"
06
07
0,
#1525
1"
1,
1G
b1 F
b10 Q
1>
1=
b1 N
1A
1D
1(
#1550
b10101001101 *
0"
0,
#1575
1"
1,
b10 F
0=
1<
#1600
b1010011011 *
0"
0,
#1625
1"
1,
0G
b11 F
0>
1=
0D
0(
#1650
b10100110110 *
0"
0,
#1675
1"
1,
1G
b100 F
1>
0=
0<
1;
1D
1(
#1700
b1001101101 *
0"
0,
#1725
1"
1,
0G
b101 F
0>
1=
0D
0(
#1750
b10011011010 *
0"
0,
#1775
1"
1,
1G
b110 F
1>
0=
1<
1D
1(
#1800
b110110101 *
0"
0,
#1825
1"
1,
0G
b111 F
0>
1=
0D
0(
#1850
b1101101010 *
0"
0,
#1875
1"
1,
b1000 F
0=
0<
0;
1:
b100 R
#1900
b11011010100 *
0"
0,
#1925
1"
1,
b100 Q
b11 N
b0 R
1@
1D
1(
#1950
b10110101001 *
0"
0,
#1975
1"
1,
b0 Q
0P
0)
#2000
0"
0,
#2025
1"
1,
#2050
1%
0"
16
0,
1P
1O
b1 R
1)
19
#2075
1"
1,
b0 F
b1 Q
0:
0O
b0 N
b10 R
09
0A
0@
0D
0(
#2100
0%
b1101010010 *
0"
06
0,
#2125
1"
1,
1G
b1 F
b10 Q
1>
1=
b1 N
1A
1D
1(
#2150
b11010100101 *
0"
0,
#2175
1"
1,
b10 F
0=
1<
#2200
b10101001011 *
1%
b101001 $
0"
16
04
0,
0E
0?
#2225
1"
1,
0G
b11 F
0>
1=
0D
0(
#2250
0%
b1010010110 *
0"
06
0,
#2275
1"
1,
1G
b100 F
1>
0=
0<
1;
1D
1(
#2300
b10100101101 *
0"
0,
#2325
1"
1,
0G
b101 F
0>
1=
0D
0(
#2350
b1001011010 *
0"
0,
#2375
1"
1,
1G
b110 F
1>
0=
1<
1D
1(
#2400
b10010110101 *
0"
0,
#2425
1"
1,
0G
b111 F
0>
1=
0D
0(
#2450
b101101010 *
0"
0,
#2475
1"
1,
b1000 F
0=
0<
0;
1:
b100 R
#2500
b1011010100 *
0"
0,
#2525
1"
1,
b100 Q
b11 N
b0 R
1@
1D
1(
#2550
b10110101001 *
0"
0,
#2575
1"
1,
b0 Q
0P
0)
